[{"-2": {"good_fact_added": null, "bad_fact_added": null, "disinformer_spent_cost": 0, "mitigator_spent_cost": 0, "good_entity_rank": 5, "bad_entity_rank": 1, "head_preds": null, "tail_preds": null}, "0": {"good_fact_added": null, "bad_fact_added": null, "disinformer_spent_cost": 0, "mitigator_spent_cost": 0, "good_entity_rank": 15, "bad_entity_rank": 8, "head_preds": null, "tail_preds": null}, "1": {"good_fact_added": ["/m/06pj8", "/award/award_nominee/award_nominations./award/award_nomination/nominated_for", "/m/08xvpn"], "bad_fact_added": ["/m/06pj8", "/award/award_nominee/award_nominations./award/award_nomination/nominated_for", "/m/07024"], "disinformer_spent_cost": 1.0, "mitigator_spent_cost": 1.0, "good_entity_rank": 16, "bad_entity_rank": 3, "head_preds": ["/m/01r216", "/m/0js9s", "/m/02q_cc", "/m/06pj8", "/m/017s11"], "tail_preds": ["/m/0hx4y", "/m/012mrr", "/m/07024", "/m/011wtv", "/m/0bt4g"]}, "2": {"good_fact_added": ["/m/06jrhz", "/award/award_winner/awards_won./award/award_honor/award_winner", "/m/06pj8"], "bad_fact_added": ["/m/06pj8", "/award/award_nominee/award_nominations./award/award_nomination/nominated_for", "/m/012mrr"], "disinformer_spent_cost": 1.0, "mitigator_spent_cost": 2.572209372642415e-56, "good_entity_rank": 14, "bad_entity_rank": 4, "head_preds": ["/m/01r216", "/m/0js9s", "/m/02q_cc", "/m/06pj8", "/m/017s11"], "tail_preds": ["/m/012mrr", "/m/0hx4y", "/m/011wtv", "/m/07024", "/m/08xvpn"]}, "3": {"good_fact_added": ["/m/012mrr", "/film/film/written_by", "/m/06pj8"], "bad_fact_added": ["/m/0bxtg", "/award/award_nominee/award_nominations./award/award_nomination/award_nominee", "/m/06pj8"], "disinformer_spent_cost": 5.521082277028533e-42, "mitigator_spent_cost": 3.4811068399043105e-57, "good_entity_rank": 16, "bad_entity_rank": 3, "head_preds": ["/m/01r216", "/m/0js9s", "/m/02q_cc", "/m/06pj8", "/m/017s11"], "tail_preds": ["/m/012mrr", "/m/0hx4y", "/m/07024", "/m/011wtv", "/m/08xvpn"]}, "4": {"good_fact_added": ["/m/0h21v2", "/film/film/produced_by", "/m/06pj8"], "bad_fact_added": ["/m/02qjpv5", "/award/award_nominee/award_nominations./award/award_nomination/award_nominee", "/m/06pj8"], "disinformer_spent_cost": 2.572203558601929e-56, "mitigator_spent_cost": 0.0, "good_entity_rank": 20, "bad_entity_rank": 2, "head_preds": ["/m/01r216", "/m/0js9s", "/m/02q_cc", "/m/06pj8", "/m/017s11"], "tail_preds": ["/m/012mrr", "/m/07024", "/m/0hx4y", "/m/011wtv", "/m/01s7w3"]}, "5": {"good_fact_added": ["/m/01f7jt", "/film/film/executive_produced_by", "/m/06pj8"], "bad_fact_added": ["/m/02pqp12", "/award/award_category/winners./award/award_honor/award_winner", "/m/06pj8"], "disinformer_spent_cost": 1.2805694985172244e-57, "mitigator_spent_cost": 2.950430344240276e-73, "good_entity_rank": 25, "bad_entity_rank": 2, "head_preds": ["/m/0js9s", "/m/01r216", "/m/02q_cc", "/m/017s11", "/m/06pj8"], "tail_preds": ["/m/012mrr", "/m/07024", "/m/0hx4y", "/m/011wtv", "/m/01flv_"]}, "6": {"good_fact_added": ["/m/06pj8", "/award/award_nominee/award_nominations./award/award_nomination/award_nominee", "/m/0js9s"], "bad_fact_added": ["/m/06pj8", "/award/award_nominee/award_nominations./award/award_nomination/award_nominee", "/m/05m9f9"], "disinformer_spent_cost": 4.186393999246091e-51, "mitigator_spent_cost": 4.1863939993042314e-51, "good_entity_rank": 20, "bad_entity_rank": 3, "head_preds": ["/m/01r216", "/m/0js9s", "/m/02q_cc", "/m/017s11", "/m/06pj8"], "tail_preds": ["/m/012mrr", "/m/0hx4y", "/m/07024", "/m/011wtv", "/m/01s7w3"]}, "7": {"good_fact_added": ["/m/07r1h", "/base/popstra/celebrity/friendship./base/popstra/friendship/participant", "/m/06pj8"], "bad_fact_added": ["/m/09q_6t", "/award/award_ceremony/awards_presented./award/award_honor/award_winner", "/m/06pj8"], "disinformer_spent_cost": 0.0, "mitigator_spent_cost": 5.166420632837861e-55, "good_entity_rank": 16, "bad_entity_rank": 2, "head_preds": ["/m/02q_cc", "/m/01r216", "/m/0js9s", "/m/06pj8", "/m/017s11"], "tail_preds": ["/m/012mrr", "/m/07024", "/m/0hx4y", "/m/011wtv", "/m/0bt4g"]}, "8": {"good_fact_added": ["/m/0js9s", "/award/award_nominee/award_nominations./award/award_nomination/award_nominee", "/m/06pj8"], "bad_fact_added": ["/m/06pj8", "/award/award_nominee/award_nominations./award/award_nomination/award_nominee", "/m/0bxtg"], "disinformer_spent_cost": 4.186393999246091e-51, "mitigator_spent_cost": 2.5065674758999535e-46, "good_entity_rank": 17, "bad_entity_rank": 5, "head_preds": ["/m/01r216", "/m/0js9s", "/m/02q_cc", "/m/06pj8", "/m/017s11"], "tail_preds": ["/m/012mrr", "/m/0hx4y", "/m/011wtv", "/m/0bt4g", "/m/07024"]}, "9": {"good_fact_added": ["/m/02q_cc", "/award/award_nominee/award_nominations./award/award_nomination/award_nominee", "/m/06pj8"], "bad_fact_added": ["/m/07024", "/award/award_winning_work/awards_won./award/award_honor/award_winner", "/m/06pj8"], "disinformer_spent_cost": 2.9374821117108028e-30, "mitigator_spent_cost": 3.392270193026015e-47, "good_entity_rank": 12, "bad_entity_rank": 3, "head_preds": ["/m/01r216", "/m/0js9s", "/m/02q_cc", "/m/06pj8", "/m/017s11"], "tail_preds": ["/m/012mrr", "/m/0hx4y", "/m/07024", "/m/01flv_", "/m/011wtv"]}, "10": {"good_fact_added": ["/m/011xg5", "/film/film/written_by", "/m/06pj8"], "bad_fact_added": ["/m/06pj8", "/award/award_winner/awards_won./award/award_honor/award_winner", "/m/02qjpv5"], "disinformer_spent_cost": 6.991984182605432e-56, "mitigator_spent_cost": 4.7111658015535965e-58, "good_entity_rank": 21, "bad_entity_rank": 3, "head_preds": ["/m/01r216", "/m/0js9s", "/m/02q_cc", "/m/06pj8", "/m/017s11"], "tail_preds": ["/m/012mrr", "/m/0h21v2", "/m/07024", "/m/0hx4y", "/m/011wtv"]}, "11": {"good_fact_added": ["/m/06pj8", "/film/director/film", "/m/012mrr"], "bad_fact_added": ["/m/06pj8", "/award/award_nominee/award_nominations./award/award_nomination/award", "/m/040njc"], "disinformer_spent_cost": 3.481048699499451e-57, "mitigator_spent_cost": 5.166420632837861e-55, "good_entity_rank": 18, "bad_entity_rank": 1, "head_preds": ["/m/01r216", "/m/0js9s", "/m/02q_cc", "/m/06pj8", "/m/017s11"], "tail_preds": ["/m/07024", "/m/0hx4y", "/m/0bt4g", "/m/01s7w3", "/m/011wtv"]}, "12": {"good_fact_added": ["/m/06pj8", "/people/person/profession", "/m/0dxtg"], "bad_fact_added": ["/m/02qjpv5", "/award/award_winner/awards_won./award/award_honor/award_winner", "/m/06pj8"], "disinformer_spent_cost": 2.572203558601929e-56, "mitigator_spent_cost": 6.991989996645917e-56, "good_entity_rank": 19, "bad_entity_rank": 1, "head_preds": ["/m/01r216", "/m/0js9s", "/m/02q_cc", "/m/06pj8", "/m/017s11"], "tail_preds": ["/m/07024", "/m/0hx4y", "/m/011wtv", "/m/01s7w3", "/m/0bt4g"]}, "13": {"good_fact_added": ["/m/06pj8", "/award/award_nominee/award_nominations./award/award_nomination/award_nominee", "/m/030_3z"], "bad_fact_added": ["/m/0gq9h", "/award/award_category/winners./award/award_honor/award_winner", "/m/06pj8"], "disinformer_spent_cost": 7.281290178321643e-33, "mitigator_spent_cost": 4.1863939993042314e-51, "good_entity_rank": 11, "bad_entity_rank": 1, "head_preds": ["/m/0js9s", "/m/01r216", "/m/02q_cc", "/m/06pj8", "/m/017s11"], "tail_preds": ["/m/07024", "/m/0hx4y", "/m/011wtv", "/m/08xvpn", "/m/01s7w3"]}, "14": {"good_fact_added": ["/m/06pj8", "/organization/organization_founder/organizations_founded", "/m/030_1_"], "bad_fact_added": ["/m/06pj8", "/award/award_nominee/award_nominations./award/award_nomination/award", "/m/02pqp12"], "disinformer_spent_cost": 3.481048699499451e-57, "mitigator_spent_cost": 1.9006199352650016e-55, "good_entity_rank": 10, "bad_entity_rank": 2, "head_preds": ["/m/01r216", "/m/0js9s", "/m/02q_cc", "/m/06pj8", "/m/017s11"], "tail_preds": ["/m/0hx4y", "/m/07024", "/m/015g28", "/m/011wtv", "/m/08xvpn"]}, "15": {"good_fact_added": ["/m/08xvpn", "/film/film/produced_by", "/m/06pj8"], "bad_fact_added": ["/m/06pj8", "/award/award_nominee/award_nominations./award/award_nomination/award", "/m/0gq9h"], "disinformer_spent_cost": 3.481048699499451e-57, "mitigator_spent_cost": 3.174358547477212e-60, "good_entity_rank": 7, "bad_entity_rank": 1, "head_preds": ["/m/0js9s", "/m/01r216", "/m/02q_cc", "/m/06pj8", "/m/017s11"], "tail_preds": ["/m/07024", "/m/0hx4y", "/m/08xvpn", "/m/011wtv", "/m/0bt4g"]}, "16": {"good_fact_added": ["/m/06pj8", "/tv/tv_producer/programs_produced./tv/tv_producer_term/program", "/m/0vhm"], "bad_fact_added": ["/m/06pj8", "/award/award_winner/awards_won./award/award_honor/award_winner", "/m/05mvd62"], "disinformer_spent_cost": 6.991984182605432e-56, "mitigator_spent_cost": 4.7111658015535965e-58, "good_entity_rank": 11, "bad_entity_rank": 1, "head_preds": ["/m/0js9s", "/m/01r216", "/m/02q_cc", "/m/06pj8", "/m/017s11"], "tail_preds": ["/m/07024", "/m/0hx4y", "/m/08xvpn", "/m/011wtv", "/m/0bt4g"]}, "17": {"good_fact_added": ["/m/0js9s", "/award/award_winner/awards_won./award/award_honor/award_winner", "/m/06pj8"], "bad_fact_added": ["/m/0bxtg", "/award/award_winner/awards_won./award/award_honor/award_winner", "/m/06pj8"], "disinformer_spent_cost": 5.521082277028533e-42, "mitigator_spent_cost": 2.5065674758999535e-46, "good_entity_rank": 9, "bad_entity_rank": 1, "head_preds": ["/m/01r216", "/m/0js9s", "/m/02q_cc", "/m/06pj8", "/m/017s11"], "tail_preds": ["/m/07024", "/m/0hx4y", "/m/08xvpn", "/m/011wtv", "/m/0bt4g"]}, "18": {"good_fact_added": ["/m/06pj8", "/award/award_nominee/award_nominations./award/award_nomination/award", "/m/02qyxs5"], "bad_fact_added": ["/m/02ywhz", "/award/award_ceremony/awards_presented./award/award_honor/award_winner", "/m/06pj8"], "disinformer_spent_cost": 3.116218142618254e-60, "mitigator_spent_cost": 3.4811068399043105e-57, "good_entity_rank": 10, "bad_entity_rank": 1, "head_preds": ["/m/01r216", "/m/0js9s", "/m/02q_cc", "/m/06pj8", "/m/017s11"], "tail_preds": ["/m/07024", "/m/08xvpn", "/m/0hx4y", "/m/011wtv", "/m/0bt4g"]}, "19": {"good_fact_added": ["/m/02q_cc", "/award/award_winner/awards_won./award/award_honor/award_winner", "/m/06pj8"], "bad_fact_added": ["/m/0260bz", "/film/film/produced_by", "/m/06pj8"], "disinformer_spent_cost": 2.572203558601929e-56, "mitigator_spent_cost": 3.392270193026015e-47, "good_entity_rank": 9, "bad_entity_rank": 1, "head_preds": ["/m/01r216", "/m/0js9s", "/m/02q_cc", "/m/06pj8", "/m/017s11"], "tail_preds": ["/m/07024", "/m/0hx4y", "/m/08xvpn", "/m/0h21v2", "/m/01s7w3"]}, "20": {"good_fact_added": ["/m/06pj8", "/award/award_nominee/award_nominations./award/award_nomination/award", "/m/0drtkx"], "bad_fact_added": ["/m/06pj8", "/people/person/places_lived./people/place_lived/location", "/m/0rk71"], "disinformer_spent_cost": 2.339737298057018e-59, "mitigator_spent_cost": 3.4811068399043105e-57, "good_entity_rank": 9, "bad_entity_rank": 1, "head_preds": ["/m/01r216", "/m/0js9s", "/m/02q_cc", "/m/06pj8", "/m/017s11"], "tail_preds": ["/m/07024", "/m/0hx4y", "/m/08xvpn", "/m/011wtv", "/m/0bt4g"]}}]