[{"-2": {"good_fact_added": null, "bad_fact_added": null, "disinformer_spent_cost": 0, "mitigator_spent_cost": 0, "good_entity_rank": 4, "bad_entity_rank": 1, "head_preds": null, "tail_preds": null}, "0": {"good_fact_added": null, "bad_fact_added": null, "disinformer_spent_cost": 0, "mitigator_spent_cost": 0, "good_entity_rank": 21, "bad_entity_rank": 5, "head_preds": null, "tail_preds": null}, "1": {"good_fact_added": ["/m/0c6qh", "/celebrities/celebrity/celebrity_friends./celebrities/friendship/friend", "/m/014zcr"], "bad_fact_added": ["/m/02d4ct", "/award/award_nominee/award_nominations./award/award_nomination/award_nominee", "/m/014zcr"], "disinformer_spent_cost": 1.0, "mitigator_spent_cost": 1.0, "good_entity_rank": 46, "bad_entity_rank": 8, "head_preds": ["/m/02p65p", "/m/013knm", "/m/02pqgt8", "/m/01r93l", "/m/02t_vx"], "tail_preds": ["/m/029k4p", "/m/0gg5qcw", "/m/078sj4", "/m/049mql", "/m/01jrbv"]}, "2": {"good_fact_added": ["/m/0bsb4j", "/base/popstra/celebrity/friendship./base/popstra/friendship/participant", "/m/014zcr"], "bad_fact_added": ["/m/0bsb4j", "/award/award_winner/awards_won./award/award_honor/award_winner", "/m/014zcr"], "disinformer_spent_cost": 6.14421235332821e-06, "mitigator_spent_cost": 8.31528719103568e-07, "good_entity_rank": 26, "bad_entity_rank": 6, "head_preds": ["/m/02p65p", "/m/013knm", "/m/01zg98", "/m/0pmhf", "/m/01r93l"], "tail_preds": ["/m/029k4p", "/m/0gg5qcw", "/m/078sj4", "/m/01z452", "/m/06z8s_"]}}]